Products.DateRangeInRangeIndex-2.0.2-py3.12-nspkg.pth
Products/DateRangeInRangeIndex/__init__.py
Products/DateRangeInRangeIndex/configure.zcml
Products/DateRangeInRangeIndex/exportimport.py
Products/DateRangeInRangeIndex/index.py
Products/DateRangeInRangeIndex/index.rst
Products/DateRangeInRangeIndex/interfaces.py
Products/DateRangeInRangeIndex/tests.py
Products/DateRangeInRangeIndex/zopeindex.py
Products/DateRangeInRangeIndex/zopeindex.rst
Products/DateRangeInRangeIndex/www/addDRIRIndex.zpt
Products/DateRangeInRangeIndex/www/index.gif
Products/DateRangeInRangeIndex/www/manageDRIRIndex.zpt
Products.DateRangeInRangeIndex-2.0.2.dist-info/LICENSE.rst
Products.DateRangeInRangeIndex-2.0.2.dist-info/METADATA
Products.DateRangeInRangeIndex-2.0.2.dist-info/WHEEL
Products.DateRangeInRangeIndex-2.0.2.dist-info/entry_points.txt
Products.DateRangeInRangeIndex-2.0.2.dist-info/namespace_packages.txt
Products.DateRangeInRangeIndex-2.0.2.dist-info/top_level.txt
Products.DateRangeInRangeIndex-2.0.2.dist-info/zip-safe
Products.DateRangeInRangeIndex-2.0.2.dist-info/RECORD
