Metadata-Version: 2.1
Name: Products.DateRangeInRangeIndex
Version: 2.0.2
Summary: Zope index to query a daterange on objects with a daterange
Home-page: https://github.com/collective/Products.DateRangeInRangeIndex
Author: BlueDynamics Alliance
Author-email: dev@bluedynamics.com
License: Simplified BSD
Keywords: date start end range query zope index catalog overlap
Classifier: Development Status :: 5 - Production/Stable
Classifier: Operating System :: OS Independent
Classifier: Framework :: Zope :: 2
Classifier: Framework :: Zope :: 3
Classifier: Programming Language :: Python :: 2
Classifier: Programming Language :: Python :: 2.7
Classifier: Programming Language :: Python :: 3
Classifier: Programming Language :: Python :: 3.5
Classifier: Programming Language :: Python :: 3.6
Classifier: Programming Language :: Python :: 3.7
Classifier: Programming Language :: Python :: Implementation :: CPython
Classifier: Topic :: Software Development
Classifier: Topic :: Internet :: WWW/HTTP :: Dynamic Content
Classifier: License :: OSI Approved :: BSD License
License-File: LICENSE.rst
Requires-Dist: AccessControl
Requires-Dist: setuptools
Requires-Dist: Zope
Requires-Dist: Products.ZCatalog>=4.0a2
Requires-Dist: zope.catalog
Provides-Extra: test
Requires-Dist: interlude; extra == "test"
Provides-Extra: gs
Requires-Dist: Products.GenericSetup; extra == "gs"
